<?xml version="1.0"?>
<ArrayOfStation xmlns:xsi="http://www.w3.org/2001/XMLSchema-instance" xmlns:xsd="http://www.w3.org/2001/XMLSchema">
  <Station>
    <ID>122000</ID>
    <Name>Station 0</Name>
    <ChargeSlots>13</ChargeSlots>
    <Latitude>35.229</Latitude>
    <Longitude>31.7426</Longitude>
  </Station>
  <Station>
    <ID>122001</ID>
    <Name>Station 1</Name>
    <ChargeSlots>10</ChargeSlots>
    <Latitude>35.2567</Latitude>
    <Longitude>31.7676</Longitude>
  </Station>
  <Station>
    <ID>122002</ID>
    <Name>Station 2</Name>
    <ChargeSlots>6</ChargeSlots>
    <Latitude>35.1702</Latitude>
    <Longitude>31.7854</Longitude>
  </Station>
  <Station>
    <ID>122003</ID>
    <Name>Station 3</Name>
    <ChargeSlots>4</ChargeSlots>
    <Latitude>35.245</Latitude>
    <Longitude>31.7869</Longitude>
  </Station>
  <Station>
    <ID>122004</ID>
    <Name>Station 4</Name>
    <ChargeSlots>10</ChargeSlots>
    <Latitude>35.2165</Latitude>
    <Longitude>31.8051</Longitude>
  </Station>
  <Station>
    <ID>122005</ID>
    <Name>Station 5</Name>
    <ChargeSlots>10</ChargeSlots>
    <Latitude>35.2151</Latitude>
    <Longitude>31.7377</Longitude>
  </Station>
  <Station>
    <ID>122006</ID>
    <Name>Station 6</Name>
    <ChargeSlots>11</ChargeSlots>
    <Latitude>35.2105</Latitude>
    <Longitude>31.7381</Longitude>
  </Station>
  <Station>
    <ID>122007</ID>
    <Name>Station 7</Name>
    <ChargeSlots>10</ChargeSlots>
    <Latitude>35.1674</Latitude>
    <Longitude>31.7728</Longitude>
  </Station>
  <Station>
    <ID>122008</ID>
    <Name>Station 8</Name>
    <ChargeSlots>9</ChargeSlots>
    <Latitude>35.1858</Latitude>
    <Longitude>31.7539</Longitude>
  </Station>
  <Station>
    <ID>122009</ID>
    <Name>Station 9</Name>
    <ChargeSlots>8</ChargeSlots>
    <Latitude>35.1731</Latitude>
    <Longitude>31.7705</Longitude>
  </Station>
</ArrayOfStation>